mastercardapicore/__init__.py
mastercardapicore/version.py
mastercardapicore/core/__init__.py
mastercardapicore/core/baseobject.py
mastercardapicore/core/config.py
mastercardapicore/core/constants.py
mastercardapicore/core/controller.py
mastercardapicore/core/exceptions.py
mastercardapicore/core/model.py
mastercardapicore/core/util.py
mastercardapicore/security/__init__.py
mastercardapicore/security/authentication.py
mastercardapicore/security/oauth.py
mastercardapicore/security/util.py
mastercard_api_client-2.0.3.dist-info/METADATA
mastercard_api_client-2.0.3.dist-info/WHEEL
mastercard_api_client-2.0.3.dist-info/RECORD
