Metadata-Version: 2.3
Name: mastercard-api-client
Version: 2.0.3
Summary: MasterCard API Python Core SDK, fork of the mastercard-api-core library.
Author-email: Twisto Platform <platform@twisto.cz>
Classifier: Intended Audience :: Developers
Classifier: Operating System :: OS Independent
Classifier: Programming Language :: Python
Classifier: Programming Language :: Python :: 3.8
Classifier: Programming Language :: Python :: 3.9
Classifier: Programming Language :: Python :: 3.10
Classifier: Programming Language :: Python :: 3.11
Classifier: Programming Language :: Python :: 3.12
Classifier: Programming Language :: Python :: Implementation :: CPython
Classifier: Programming Language :: Python :: Implementation :: PyPy
Requires-Python: >=3.8
Requires-Dist: cryptography>=42.0.5
Requires-Dist: future>=0.18.3
Requires-Dist: requests>=2.31.0
